<?xml version="1.0" encoding="UTF-8"?>
<recipe>
	<cloth1>
		<top>
			<opacity>models/cloth1/cloth1fbm/cloth1top.png</opacity>
			<data>models/cloth1/upcloth.json</data></top>
		<bottom>
			<opacity>models/cloth1/cloth1fbm/cloth1bottom.png</opacity>
			<data>models/cloth1/trousers.json</data></bottom>
		<hair>
			<data>models/cloth1/hair.json</data></hair>
		<eyewear>
			<data>models/cloth1/glasses.json</data></eyewear>
		<shoes>
			<opacity>models/cloth1/cloth1fbm/cloth1shoes.png</opacity>
			<data>models/cloth1/shoes.json</data></shoes>
		<map>
			<diffuse>models/cloth1/cloth1fbm/cloth1_Packed0_Diffuse.png</diffuse>
			<specular>models/cloth1/cloth1fbm/cloth1_Packed0_Specular.png</specular>
			<normal>models/cloth1/cloth1fbm/cloth1_Packed0_Normal.png</normal>
			<opacity>models/cloth1/cloth1fbm/cloth1_Packed0_Opacity.png</opacity>
			<lighting>models/cloth1/cloth1fbm/cloth1_LightingMap.png</lighting>
		</map>
	</cloth1>
	<cloth2>
		<top>
			<opacity></opacity>
			<data></data></top>
		<bottom>
			<opacity></opacity>
			<data></data></bottom>
		<hair>
			<data></data></hair>
		<eyewear>
			<data></data></eyewear>
		<shoes>
			<opacity></opacity>
			<data></data></shoes>
		<map>
			<diffuse></diffuse>
			<specular></specular>
			<normal></normal>
			<opacity></opacity>
			<lighting></lighting>
		</map>
	</cloth2>
	<cloth3>
		<top>
			<opacity></opacity>
			<data></data></top>
		<bottom>
			<opacity></opacity>
			<data></data></bottom>
		<hair>
			<data></data></hair>
		<eyewear>
			<data></data></eyewear>
		<shoes>
			<opacity></opacity>
			<data></data></shoes>
		<map>
			<diffuse></diffuse>
			<specular></specular>
			<normal></normal>
			<opacity></opacity>
			<lighting></lighting>
		</map>
	</cloth3>
	<cloth4>
		<top>
			<opacity></opacity>
			<data></data></top>
		<bottom>
			<opacity></opacity>
			<data></data></bottom>
		<hair>
			<data></data></hair>
		<eyewear>
			<data></data></eyewear>
		<shoes>
			<opacity></opacity>
			<data></data></shoes>
		<map>
			<diffuse></diffuse>
			<specular></specular>
			<normal></normal>
			<opacity></opacity>
			<lighting></lighting>
		</map>
	</cloth4>
	<cloth5>
		<top>
			<opacity></opacity>
			<data></data></top>
		<bottom>
			<opacity></opacity>
			<data></data></bottom>
		<hair>
			<data></data></hair>
		<eyewear>
			<data></data></eyewear>
		<shoes>
			<opacity></opacity>
			<data></data></shoes>
		<map>
			<diffuse></diffuse>
			<specular></specular>
			<normal></normal>
			<opacity></opacity>
			<lighting></lighting>
		</map>
	</cloth5>
</recipe>